setup.py
aioclickhouse/__init__.py
aioclickhouse/connection.py
aioclickhouse/error.py
aioclickhouse/response.py
aioclickhouse/tsv.py
aioclickhouse.egg-info/PKG-INFO
aioclickhouse.egg-info/SOURCES.txt
aioclickhouse.egg-info/dependency_links.txt
aioclickhouse.egg-info/requires.txt
aioclickhouse.egg-info/top_level.txt