Metadata-Version: 1.1
Name: aioclickhouse
Version: 0.0.7
Summary: Asynchronous connector to ClickHouse DBMS
Home-page: https://bitbucket.org/new_ios_team/py_clickhouse_aio
Author: Dmitry Sobolev
Author-email: ds@napoleonit.ru
License: UNKNOWN
Platform: UNKNOWN
Classifier: Development Status :: 3 - Alpha
Classifier: Programming Language :: Python :: 3.5
Classifier: Programming Language :: Python :: 3.6
Classifier: Topic :: Database
